prop_profiler/__init__.py
prop_profiler/cli.py
prop_profiler/profiler.py
prop_profiler/py.typed
prop_profiler/update_model.py
prop_profiler/data/__init__.py
prop_profiler/data/loader.py
prop_profiler/external/__init__.py
prop_profiler/external/MolGpKa/ATTRIBUTION.md
prop_profiler/external/MolGpKa/LICENSE.md
prop_profiler/external/MolGpKa/__init__.py
prop_profiler/external/MolGpKa/predict_pka.py
prop_profiler/external/MolGpKa/utils/README.md
prop_profiler/external/MolGpKa/utils/__init__.py
prop_profiler/external/MolGpKa/utils/descriptor.py
prop_profiler/external/MolGpKa/utils/gcn_conv.py
prop_profiler/external/MolGpKa/utils/inits.py
prop_profiler/external/MolGpKa/utils/ionization_group.py
prop_profiler/external/MolGpKa/utils/net.py
prop_profiler/external/MolGpKa/utils/smarts_pattern.tsv
prop_profiler/model_weights/esol_model.pkl.gz
prop_profiler/model_weights/logd_model.pkl.gz
prop_profiler/model_weights/weight_acid.pth
prop_profiler/model_weights/weight_base.pth
prop_profiler/models/base_wrapper.py
prop_profiler/models/cns_mpo_wrapper.py
prop_profiler/models/molgpka_wrapper.py
prop_profiler/models/stoplight_wrapper.py
prop_profiler/predictors/__init__.py
prop_profiler/predictors/base.py
prop_profiler/predictors/cns_mpo.py
prop_profiler/predictors/esol.py
prop_profiler/predictors/logd.py
prop_profiler/predictors/pka.py
prop_profiler/predictors/stoplight.py
prop_profiler/training/__init__.py
prop_profiler/training/base_trainer.py
prop_profiler/utils/__init__.py
prop_profiler/utils/chem_helpers.py
prop_profiler/utils/logging.py
prop_profiler-0.2.1.dist-info/licenses/LICENSE
prop_profiler-0.2.1.dist-info/METADATA
prop_profiler-0.2.1.dist-info/WHEEL
prop_profiler-0.2.1.dist-info/entry_points.txt
prop_profiler-0.2.1.dist-info/top_level.txt
prop_profiler-0.2.1.dist-info/RECORD
