Metadata-Version: 2.4
Name: prop-profiler
Version: 0.2.1
Summary: A molecular property profiler for drug discovery applications
Author-email: Enes Kelestemur <enesk@email.unc.edu>
License-Expression: MIT
Project-URL: Homepage, https://github.com/eneskelestemur/prop_profiler
Project-URL: Repository, https://github.com/eneskelestemur/prop_profiler
Requires-Python: >=3.11
License-File: LICENSE
Requires-Dist: rdkit>=2025.9.1
Requires-Dist: scikit-learn==1.7.2
Requires-Dist: numpy
Requires-Dist: pandas
Requires-Dist: tqdm
Requires-Dist: matplotlib
Provides-Extra: pka
Requires-Dist: torch>=2.0.0; extra == "pka"
Requires-Dist: torch-geometric>=2.0.0; extra == "pka"
Provides-Extra: dev
Requires-Dist: pytest>=7.0.0; extra == "dev"
Requires-Dist: mypy>=1.10.0; extra == "dev"
Dynamic: license-file
